tap_clickcast/__init__.py
tap_clickcast/auth.py
tap_clickcast/client.py
tap_clickcast/schemas/campaigns.json
tap_clickcast/schemas/employers.json
tap_clickcast/schemas/jobs.json
tap_clickcast/schemas/jobstats.json
tap_clickcast/schemas/publishers.json
tap_clickcast/streams.py
tap_clickcast/tap.py
tap_clickcast/tests/__init__.py
tap_clickcast/tests/test_client.py
tap_clickcast-0.6.0.dist-info/METADATA
tap_clickcast-0.6.0.dist-info/WHEEL
tap_clickcast-0.6.0.dist-info/entry_points.txt
tap_clickcast-0.6.0.dist-info/RECORD
