Metadata-Version: 2.1
Name: tap-clickcast
Version: 0.6.0
Summary: `tap-clickcast` is a Singer tap for clickcast, built with the Meltano SDK for Singer Taps.
License: Apache 2.0
Author: Datateer
Requires-Python: >=3.9,<3.11
Classifier: License :: Other/Proprietary License
Classifier: Programming Language :: Python :: 3
Classifier: Programming Language :: Python :: 3.9
Classifier: Programming Language :: Python :: 3.10
Requires-Dist: requests (>=2.25.1,<3.0.0)
Requires-Dist: singer-sdk (>=0.19.0,<0.20.0)
